mgwrvisualizer/__init__.py
mgwrvisualizer/data_extractors.py
mgwrvisualizer/main.py
mgwrvisualizer/utils.py
webclient_dist/assets/index.66507afe.css
webclient_dist/assets/index.91156cc4.js
webclient_dist/assets/vendor.fe90d8ec.js
webclient_dist/favicon.ico
webclient_dist/index.html
mgwrvisualizer-0.0.3.dist-info/WHEEL
mgwrvisualizer-0.0.3.dist-info/METADATA
mgwrvisualizer-0.0.3.dist-info/RECORD
